ctrlmaniac/rps/__init__.py
ctrlmaniac/rps/__main__.py
ctrlmaniac/rps/play.py
ctrlmaniac/rps/rps.py
ctrlmaniac.rps-1.1.2.dist-info/entry_points.txt
ctrlmaniac.rps-1.1.2.dist-info/LICENSE
ctrlmaniac.rps-1.1.2.dist-info/WHEEL
ctrlmaniac.rps-1.1.2.dist-info/METADATA
ctrlmaniac.rps-1.1.2.dist-info/RECORD
