Metadata-Version: 2.1
Name: ctrlmaniac.rps
Version: 1.1.2
Summary: The famous Rock Paper Scissors game written in python
Author: Davide Di Criscito
Author-email: davide.dicriscito@gmail.com
Requires-Python: >=3.8,<4.0
Classifier: Programming Language :: Python :: 3
Classifier: Programming Language :: Python :: 3.10
Classifier: Programming Language :: Python :: 3.8
Classifier: Programming Language :: Python :: 3.9
